roper/__init__.py
roper/__main__.py
roper/lib.py
roper/tasks.py
roper-0.1.5.dist-info/LICENSE
roper-0.1.5.dist-info/METADATA
roper-0.1.5.dist-info/WHEEL
roper-0.1.5.dist-info/entry_points.txt
roper-0.1.5.dist-info/top_level.txt
roper-0.1.5.dist-info/RECORD
