Metadata-Version: 2.1
Name: roper
Version: 0.1.5
Summary: A CLI tool for the roper library.
Home-page: https://github.com/beat-no/roper
Author: Øystein S. Haaland
Author-email: oystein@beat.no
License: UNKNOWN
Platform: UNKNOWN
Requires-Dist: rope
Requires-Dist: invoke
